netconan/__init__.py
netconan/anonymize_files.py
netconan/default_pwd_regexes.py
netconan/default_reserved_words.py
netconan/ip_anonymization.py
netconan/netconan.py
netconan/sensitive_item_removal.py
netconan/utils/__init__.py
netconan/utils/juniper_secrets.py
netconan-0.14.0.dist-info/licenses/LICENSE
netconan-0.14.0.dist-info/licenses/LICENSE.email
netconan-0.14.0.dist-info/licenses/NOTICE
netconan-0.14.0.dist-info/METADATA
netconan-0.14.0.dist-info/WHEEL
netconan-0.14.0.dist-info/entry_points.txt
netconan-0.14.0.dist-info/top_level.txt
netconan-0.14.0.dist-info/RECORD
