Metadata-Version: 2.4
Name: netconan
Version: 0.14.0
Summary: Netconan network configuration anonymization utilities
Home-page: https://github.com/intentionet/netconan
Author: Intentionet
Author-email: netconan-dev@intentionet.com
License: Apache License 2.0
Keywords: network configuration anonymizer
Classifier: Development Status :: 3 - Alpha
Classifier: Intended Audience :: Developers
Classifier: Topic :: Software Development :: Libraries :: Python Modules
Classifier: License :: OSI Approved :: Apache Software License
Classifier: Programming Language :: Python :: 3
Classifier: Programming Language :: Python :: 3 :: Only
Classifier: Programming Language :: Python :: 3.9
Classifier: Programming Language :: Python :: 3.10
Classifier: Programming Language :: Python :: 3.11
Classifier: Programming Language :: Python :: 3.12
Classifier: Programming Language :: Python :: 3.13
Requires-Python: >=3.9
License-File: LICENSE
License-File: LICENSE.email
License-File: NOTICE
Requires-Dist: bidict<1.0.0
Requires-Dist: configargparse<2.0.0
Requires-Dist: passlib<2.0.0
Provides-Extra: dev
Requires-Dist: flake8<8.0.0; extra == "dev"
Requires-Dist: flake8-docstrings<2.0.0; extra == "dev"
Requires-Dist: pydocstyle<6.0.0; extra == "dev"
Provides-Extra: test
Requires-Dist: pytest<7,>=6; extra == "test"
Requires-Dist: pytest-cov<6.0.0; extra == "test"
Requires-Dist: requests_mock<2.0.0; extra == "test"
Requires-Dist: testfixtures<7.0.0; extra == "test"
Dynamic: author
Dynamic: author-email
Dynamic: classifier
Dynamic: description
Dynamic: description-content-type
Dynamic: home-page
Dynamic: keywords
Dynamic: license
Dynamic: license-file
Dynamic: provides-extra
Dynamic: requires-dist
Dynamic: requires-python
Dynamic: summary
